{
    "src": [
        "hKmFpm5Iu2k",
        "7a2zNecU8OM",
        "b-II8hWxyZI",
        "qAjFoZXSEXM",
        "YkrQs9Q5XL8",
        "L9hIstFPYQE",
        "v0xckWVpW2U",
        "7eJTeiG83Uo",
        "GS0uYMSRXxc",
        "p26-ND3k3_c",
        "3r8ti20KEEI",
        "e_ANPP1DiA8",
        "DJXLodLHNiA",
        "XOnp1SXuS2s"
    ],
    "description": {
        "MeteorS7": [
            "hKmFpm5Iu2k"
        ],
        "Latte": [
            "7a2zNecU8OM"
        ],
        "HinaRuka21": [
            "b-II8hWxyZI"
        ],
        "Memento-mori": [
            "qAjFoZXSEXM"
        ],
        "Genshin": [
            "YkrQs9Q5XL8"
        ],
        "Mizorech": [
            "L9hIstFPYQE"
        ],
        "Wecars": [
            "v0xckWVpW2U",
            "7eJTeiG83Uo",
            "GS0uYMSRXxc",
            "p26-ND3k3_c",
            "DJXLodLHNiA",
            "XOnp1SXuS2s"
        ],
        "Yukkuri-upapalon": [
            "3r8ti20KEEI"
        ],
        "Chaaaco": [
            "e_ANPP1DiA8"
        ]
    }
}
