{
    "src": [
        "fzmJgJtt5rc",
        "Ra34_PyNUuI",
        "nrflR9lh7Eo",
        "0jn-qSRKuU0",
        "YkrQs9Q5XL8",
        "XOR8wErcIB8",
        "v0xckWVpW2U",
        "7eJTeiG83Uo",
        "GS0uYMSRXxc",
        "p26-ND3k3_c",
        "3r8ti20KEEI",
        "kGzpcxPEJWc",
        "DJXLodLHNiA",
        "XOnp1SXuS2s"
    ],
    "description": {
        "MeteorS7": [
            "fzmJgJtt5rc"
        ],
        "Latte": [
            "Ra34_PyNUuI"
        ],
        "HinaRuka21": [
            "nrflR9lh7Eo"
        ],
        "Memento-mori": [
            "0jn-qSRKuU0"
        ],
        "Genshin": [
            "YkrQs9Q5XL8"
        ],
        "Mizorech": [
            "XOR8wErcIB8"
        ],
        "Wecars": [
            "v0xckWVpW2U",
            "7eJTeiG83Uo",
            "GS0uYMSRXxc",
            "p26-ND3k3_c",
            "DJXLodLHNiA",
            "XOnp1SXuS2s"
        ],
        "Yukkuri-upapalon": [
            "3r8ti20KEEI"
        ],
        "Chaaaco": [
            "kGzpcxPEJWc"
        ]
    }
}
